{
  "general": [
    {
      "id": "e8c2e93c-6b5d-42cb-af06-feab8eb6ad44",
      "title": "야구",
      "content": "보자",
      "createdAt": "2025-10-23T06:25:58.775Z"
    },
    {
      "id": "b5ddd64c-a5de-4b42-a485-d2a4d4c14bd6",
      "title": "축구",
      "content": "보자",
      "createdAt": "2025-10-23T06:26:45.833Z"
    }
  ],
  "classes": {
    "1-1": [],
    "1-2": [],
    "1-3": [],
    "1-4": [],
    "1-5": [],
    "2-1": [],
    "2-2": [],
    "2-3": [],
    "2-4": [],
    "2-5": [],
    "3-1": [],
    "3-2": [],
    "3-3": [],
    "3-4": [],
    "3-5": []
  }
}